aext_core_server/__init__.py
aext_core_server-0.0.1.dist-info/METADATA
aext_core_server-0.0.1.dist-info/WHEEL
aext_core_server-0.0.1.dist-info/RECORD
