Metadata-Version: 2.1
Name: aext-core-server
Version: 0.0.1
Summary: The aext-core-server component of anaconda-toolbox
License-Expression: BSD-3-Clause
